README.md
setup.py
BottleRoutes.egg-info/PKG-INFO
BottleRoutes.egg-info/SOURCES.txt
BottleRoutes.egg-info/dependency_links.txt
BottleRoutes.egg-info/top_level.txt
RouteExt/RouteExt.py
RouteExt/__init__.py