Metadata-Version: 2.1
Name: BottleRoutes
Version: 2020.8.20
Summary: Plugin to use OO to create routes in bottle.
Home-page: https://github.com/afonsomedeiros/BottleRoutes
Author: Afonso Medeiros
Author-email: afonso.b.medeiros@gmail.com
License: MIT
Platform: UNKNOWN
Classifier: Programming Language :: Python :: 3
Classifier: License :: OSI Approved :: MIT License
Classifier: Operating System :: OS Independent
Requires-Python: >=3.6
